{
	"metaDataVersion": "1.0.0",
	"category": "com.microchip.ide.project",
	"content": {
		"metaDataVersion": "1.1.0",
		"name": "com.microchip.mcu32.mplabx.project.net_apps_pic32mz_web_server_nvm_mpfs_pic32mz_ef_sk_freertos",
		"version": "3.7.0",
		"displayName": "TCP/IP Web Server NVM MPFS Application Example for PIC32MZ EF Family",
		"projectName": "web_server_nvm_mpfs_freertos",
		"shortDescription": "The Web Server Non-volatile Memory (NVM) MPFS configuration demonstrates creating an HTTP web server on a Microchip evaluation board.",
		"ide": {
			"name": "MPLABX",
			"semverRange": ">=5.45.0"
		},
		"compiler": [
			{
				"name": "XC32",
				"semverRange": ">=2.50.0"
			}
		],
		"dfp": {
			"name": "PIC32MZ-EF_DFP",
			"semverRange": "^1.2.51"
		},
		"configurator": {
			"name": "MHC",
			"semverRange": ">=3.6.2"
		},
		"device": {
			"metaDataVersion": "1.0.0",
			"category": "com.microchip.portal.contentRef",
			"content": {
				"metaDataVersion": "1.0.0",
				"category": "com.microchip.device",
				"name": "PIC32MZ2048EFM144",
				"versionRange": "*"
			}
		},
		"author": "Microchip",
		"subcategories": [
			[
				"Development Kit", "PIC32MZ Embedded Connectivity with FPU (EF) Starter Kit"
			],
			[
				"Harmony", "Middleware", "TCP/IP", "WEB_SERVER_NVM_MPFS"
			],
			[
				"Middleware", "TCP/IP", "WEB_SERVER_NVM_MPFS"
			]
		],
		"peripherals": [
			"MAC"
		],
		"keywords": [
			"MHC",
			"Harmony",
			"Middleware",
			"TCP/IP",
			"PIC32MZ2048EFM144",
			"PIC32MZ EF Family",
			"Ethernet MAC",
			"GMAC"
		],
		"additionalData": {
			"longDescription": {
				"metaDataVersion": "1.0.0",
				"category": "com.microchip.portal.fileRef",
				"content": {
					"metaDataVersion": "1.0.0",
					"fileName": "./../../readme.md",
					"mimeType": "text/markdown"
				}
			}
		}
	}
}